README.rst
setup.cfg
setup.py
querybuilder/__init__.py
querybuilder/helpers.py
querybuilder.egg-info/PKG-INFO
querybuilder.egg-info/SOURCES.txt
querybuilder.egg-info/dependency_links.txt
querybuilder.egg-info/pbr.json
querybuilder.egg-info/requires.txt
querybuilder.egg-info/top_level.txt
querybuilder/ext/__init__.py
querybuilder/ext/peewee.py
tests/__init__.py
tests/test_strings.py