Metadata-Version: 1.1
Name: querybuilder
Version: 0.1.1
Summary: An SQL query building specification to be used in conjunction with REST APIs and its implementation for peewee.
Home-page: https://github.com/brijeshb42/querybuilder
Author: Brijesh Bittu
Author-email: brijeshb42@gmail.com
License: http://www.opensource.org/licenses/mit-license.php
Download-URL: https://github.com/brijeshb42/querybuilder/tarball/0.1.1
Keywords: SQL,peewee,querybuilder
Platform: UNKNOWN
